napari_steinpose/__init__.py
napari_steinpose/_reader.py
napari_steinpose/_version.py
napari_steinpose/folder_list_widget.py
napari_steinpose/imc_analysis.py
napari_steinpose/napari.yaml
napari_steinpose/steinpose_widget.py
napari_steinpose/_tests/__init__.py
napari_steinpose/_tests/test_reader.py
napari_steinpose/_tests/test_widget.py
napari_steinpose/_tests/data/test_steinpose1.tiff
napari_steinpose/_tests/data/test_steinpose2.tiff
napari_steinpose-0.1.0.dist-info/LICENSE
napari_steinpose-0.1.0.dist-info/METADATA
napari_steinpose-0.1.0.dist-info/WHEEL
napari_steinpose-0.1.0.dist-info/entry_points.txt
napari_steinpose-0.1.0.dist-info/top_level.txt
napari_steinpose-0.1.0.dist-info/RECORD
