Metadata-Version: 2.1
Name: napari-steinpose
Version: 0.1.0
Summary: A plugin to process Imaging Mass Cytometry data with cellpose and steinbock
Home-page: https://github.com/guiwitz/napari-steinpose
Author: Guillaume Witz
Author-email: guillaume.witz@unibe.ch
License: BSD-3-Clause
Project-URL: Bug Tracker, https://github.com/guiwitz/napari-steinpose/issues
Project-URL: Documentation, https://github.com/guiwitz/napari-steinpose#README.md
Project-URL: Source Code, https://github.com/guiwitz/napari-steinpose
Project-URL: User Support, https://github.com/guiwitz/napari-steinpose/issues
Classifier: Development Status :: 2 - Pre-Alpha
Classifier: Framework :: napari
Classifier: Intended Audience :: Developers
Classifier: License :: OSI Approved :: BSD License
Classifier: Operating System :: OS Independent
Classifier: Programming Language :: Python
Classifier: Programming Language :: Python :: 3
Classifier: Programming Language :: Python :: 3 :: Only
Classifier: Programming Language :: Python :: 3.8
Classifier: Programming Language :: Python :: 3.9
Classifier: Topic :: Scientific/Engineering :: Image Processing
Requires-Python: >=3.8
License-File: LICENSE
Requires-Dist: torch (==1.11.0)
Requires-Dist: cellpose
Requires-Dist: numpy
Requires-Dist: magicgui
Requires-Dist: qtpy
Requires-Dist: matplotlib
Requires-Dist: readimc
Requires-Dist: steinbock
Requires-Dist: pandas
Requires-Dist: aicsimageio
Provides-Extra: testing
Requires-Dist: tox ; extra == 'testing'
Requires-Dist: pytest ; extra == 'testing'
Requires-Dist: pytest-cov ; extra == 'testing'
Requires-Dist: pytest-qt ; extra == 'testing'
Requires-Dist: napari ; extra == 'testing'
Requires-Dist: pyqt5 ; extra == 'testing'
Requires-Dist: pytest-order ; extra == 'testing'
